django_orbit-0.6.3.dist-info/licenses/LICENSE
orbit/__init__.py
orbit/apps.py
orbit/conf.py
orbit/handlers.py
orbit/health.py
orbit/helpers.py
orbit/middleware.py
orbit/mixins.py
orbit/models.py
orbit/recorders.py
orbit/stats.py
orbit/urls.py
orbit/utils.py
orbit/views.py
orbit/watchers.py
orbit/migrations/0001_initial.py
orbit/migrations/0002_alter_orbitentry_type.py
orbit/migrations/0003_alter_orbitentry_type.py
orbit/migrations/0004_alter_orbitentry_type.py
orbit/migrations/__init__.py
orbit/templates/orbit/base.html
orbit/templates/orbit/dashboard.html
orbit/templates/orbit/health.html
orbit/templates/orbit/locked.html
orbit/templates/orbit/stats.html
orbit/templates/orbit/partials/detail.html
orbit/templates/orbit/partials/feed.html
orbit/templates/orbit/partials/stats.html
orbit/templatetags/__init__.py
orbit/templatetags/orbit_tags.py
django_orbit-0.6.3.dist-info/METADATA
django_orbit-0.6.3.dist-info/WHEEL
django_orbit-0.6.3.dist-info/top_level.txt
django_orbit-0.6.3.dist-info/RECORD
