Metadata-Version: 2.4
Name: django-orbit
Version: 0.6.3
Summary: Satellite Observability for Django - A modern debugging and observability tool
Author: Django Orbit Contributors
Maintainer: Django Orbit Contributors
License: MIT
Project-URL: Homepage, https://github.com/astro-stack/django-orbit
Project-URL: Documentation, https://github.com/astro-stack/django-orbit#readme
Project-URL: Repository, https://github.com/astro-stack/django-orbit
Project-URL: Changelog, https://github.com/astro-stack/django-orbit/blob/main/CHANGELOG.md
Project-URL: Bug Tracker, https://github.com/astro-stack/django-orbit/issues
Keywords: django,debugging,observability,monitoring,telescope,profiling,debug-toolbar
Classifier: Development Status :: 4 - Beta
Classifier: Environment :: Web Environment
Classifier: Framework :: Django
Classifier: Framework :: Django :: 4.0
Classifier: Framework :: Django :: 4.1
Classifier: Framework :: Django :: 4.2
Classifier: Framework :: Django :: 5.0
Classifier: Intended Audience :: Developers
Classifier: License :: OSI Approved :: MIT License
Classifier: Operating System :: OS Independent
Classifier: Programming Language :: Python
Classifier: Programming Language :: Python :: 3
Classifier: Programming Language :: Python :: 3.9
Classifier: Programming Language :: Python :: 3.10
Classifier: Programming Language :: Python :: 3.11
Classifier: Programming Language :: Python :: 3.12
Classifier: Topic :: Software Development :: Debuggers
Classifier: Topic :: Software Development :: Libraries :: Python Modules
Classifier: Topic :: System :: Monitoring
Requires-Python: >=3.9
License-File: LICENSE
Requires-Dist: Django>=4.0
Provides-Extra: dev
Requires-Dist: pytest>=7.0; extra == "dev"
Requires-Dist: pytest-django>=4.5; extra == "dev"
Requires-Dist: pytest-cov>=4.0; extra == "dev"
Requires-Dist: black>=23.0; extra == "dev"
Requires-Dist: isort>=5.12; extra == "dev"
Requires-Dist: flake8>=6.0; extra == "dev"
Requires-Dist: mypy>=1.0; extra == "dev"
Requires-Dist: django-stubs>=4.0; extra == "dev"
Dynamic: license-file
